open_logistics/__init__.py
open_logistics/application/__init__.py
open_logistics/application/agents/__init__.py
open_logistics/application/agents/agent_manager.py
open_logistics/application/agents/mission_coordinator_agent.py
open_logistics/application/agents/resource_optimizer_agent.py
open_logistics/application/agents/supply_chain_agent.py
open_logistics/application/agents/threat_assessment_agent.py
open_logistics/application/use_cases/__init__.py
open_logistics/application/use_cases/optimize_supply_chain.py
open_logistics/application/use_cases/predict_demand.py
open_logistics/core/__init__.py
open_logistics/core/config.py
open_logistics/core/security.py
open_logistics/domain/__init__.py
open_logistics/domain/entities/__init__.py
open_logistics/domain/entities/inventory.py
open_logistics/infrastructure/__init__.py
open_logistics/infrastructure/external/__init__.py
open_logistics/infrastructure/external/sap_btp_client.py
open_logistics/infrastructure/mlx_integration/__init__.py
open_logistics/infrastructure/mlx_integration/mlx_optimizer.py
open_logistics/presentation/api/__init__.py
open_logistics/presentation/api/main.py
open_logistics/presentation/cli/main.py
open_logistics-1.0.1.dist-info/METADATA
open_logistics-1.0.1.dist-info/WHEEL
open_logistics-1.0.1.dist-info/entry_points.txt
open_logistics-1.0.1.dist-info/RECORD
